<?xml version="1.0" encoding="utf-8" standalone="no"?><ContractNotice xmlns="urn:oasis:names:specification:ubl:schema:xsd:ContractNotice-2" xmlns:cac="urn:oasis:names:specification:ubl:schema:xsd:CommonAggregateComponents-2" xmlns:cbc="urn:oasis:names:specification:ubl:schema:xsd:CommonBasicComponents-2" xmlns:efac="http://data.europa.eu/p27/eforms-ubl-extension-aggregate-components/1" xmlns:efbc="http://data.europa.eu/p27/eforms-ubl-extension-basic-components/1" xmlns:efext="http://data.europa.eu/p27/eforms-ubl-extensions/1" xmlns:ext="urn:oasis:names:specification:ubl:schema:xsd:CommonExtensionComponents-2"><ext:UBLExtensions><ext:UBLExtension><ext:ExtensionContent><efext:EformsExtension><efbc:TransmissionDate>2025-01-09+00:00</efbc:TransmissionDate><efbc:TransmissionTime>09:37:21+00:00</efbc:TransmissionTime><efac:NoticeSubType><cbc:SubTypeCode listName="notice-subtype">16</cbc:SubTypeCode></efac:NoticeSubType><efac:Organizations><efac:Organization><efac:Company><cbc:WebsiteURI>https://www.mimer.nu</cbc:WebsiteURI><cac:PartyIdentification><cbc:ID schemeName="organization">ORG-0001</cbc:ID></cac:PartyIdentification><cac:PartyName><cbc:Name languageID="SWE">Bostads AB Mimer</cbc:Name></cac:PartyName><cac:PostalAddress><cbc:StreetName>Box 1170</cbc:StreetName><cbc:Department>Inköpsenheten</cbc:Department><cbc:CityName>Västerås</cbc:CityName><cbc:PostalZone>721 29</cbc:PostalZone><cbc:CountrySubentityCode listName="nuts">SE125</cbc:CountrySubentityCode><cac:Country><cbc:IdentificationCode listName="country">SWE</cbc:IdentificationCode></cac:Country></cac:PostalAddress><cac:PartyLegalEntity><cbc:CompanyID schemeID="002">5560193384</cbc:CompanyID></cac:PartyLegalEntity><cac:Contact><cbc:Name>Jasmin Bargabriel</cbc:Name><cbc:Telephone>+46 (0)21 39 70 00</cbc:Telephone><cbc:ElectronicMail>Jasmin.Bargabriel@mimer.nu</cbc:ElectronicMail></cac:Contact></efac:Company></efac:Organization><efac:Organization><efac:Company><cbc:WebsiteURI>https://www.domstol.se/forvaltningsratten-i-uppsala/</cbc:WebsiteURI><cac:PartyIdentification><cbc:ID schemeName="organization">ORG-0002</cbc:ID></cac:PartyIdentification><cac:PartyName><cbc:Name languageID="SWE">Förvaltningsrätten</cbc:Name></cac:PartyName><cac:PostalAddress><cbc:StreetName>Box 1853</cbc:StreetName><cbc:CityName>Uppsala</cbc:CityName><cbc:PostalZone>751 48</cbc:PostalZone><cbc:CountrySubentityCode listName="nuts">SE121</cbc:CountrySubentityCode><cac:Country><cbc:IdentificationCode listName="country">SWE</cbc:IdentificationCode></cac:Country></cac:PostalAddress><cac:PartyLegalEntity><cbc:CompanyID schemeID="002">202100-2742</cbc:CompanyID></cac:PartyLegalEntity><cac:Contact><cbc:Telephone>018-431 63 00</cbc:Telephone><cbc:ElectronicMail>forvaltningsratteniuppsala@dom.se</cbc:ElectronicMail></cac:Contact></efac:Company></efac:Organization></efac:Organizations><efac:Publication><efbc:NoticePublicationID schemeName="ojs-notice-id">00015461-2025</efbc:NoticePublicationID><efbc:GazetteID schemeName="ojs-id">7/2025</efbc:GazetteID><efbc:PublicationDate>2025-01-10+01:00</efbc:PublicationDate></efac:Publication></efext:EformsExtension></ext:ExtensionContent></ext:UBLExtension></ext:UBLExtensions><cbc:UBLVersionID>2.3</cbc:UBLVersionID><cbc:CustomizationID>eforms-sdk-1.7</cbc:CustomizationID><cbc:ID schemeName="notice-id">12fe047d-7ac8-438f-9d83-57dbb2f4d001</cbc:ID><cbc:ContractFolderID>f92c6955-c529-47d2-a3a0-d77fd54d4766</cbc:ContractFolderID><cbc:IssueDate>2025-01-09+00:00</cbc:IssueDate><cbc:IssueTime>09:37:11+00:00</cbc:IssueTime><cbc:VersionID>01</cbc:VersionID><cbc:RegulatoryDomain>32014L0024</cbc:RegulatoryDomain><cbc:NoticeTypeCode listName="competition">cn-standard</cbc:NoticeTypeCode><cbc:NoticeLanguageCode>SWE</cbc:NoticeLanguageCode><cac:ContractingParty><cac:ContractingPartyType><cbc:PartyTypeCode listName="buyer-legal-type">ra</cbc:PartyTypeCode></cac:ContractingPartyType><cac:ContractingActivity><cbc:ActivityTypeCode listName="authority-activity">hc-am</cbc:ActivityTypeCode></cac:ContractingActivity><cac:Party><cac:PartyIdentification><cbc:ID schemeName="organization">ORG-0001</cbc:ID></cac:PartyIdentification></cac:Party></cac:ContractingParty><cac:TenderingTerms><cac:TendererQualificationRequest><cac:SpecificTendererRequirement><cbc:TendererRequirementTypeCode listName="exclusion-ground">finan-laund</cbc:TendererRequirementTypeCode><cbc:Description languageID="SWE">Kap. 13</cbc:Description></cac:SpecificTendererRequirement></cac:TendererQualificationRequest></cac:TenderingTerms><cac:TenderingProcess><cbc:ProcedureCode listName="procurement-procedure-type">open</cbc:ProcedureCode><cac:ProcessJustification><cbc:ProcessReasonCode listName="accelerated-procedure">false</cbc:ProcessReasonCode></cac:ProcessJustification></cac:TenderingProcess><cac:ProcurementProject><cbc:ID schemeName="InternalID">2024140</cbc:ID><cbc:Name languageID="SWE">Måleriarbeten lägenhetsunderhåll</cbc:Name><cbc:Description languageID="SWE">Ramavtal för inre måleriarbeten (lägenhetsunderhåll) i beställarens fastighetsbestånd</cbc:Description><cbc:ProcurementTypeCode listName="contract-nature">works</cbc:ProcurementTypeCode><cac:RequestedTenderTotal><cbc:EstimatedOverallContractAmount currencyID="SEK">60000000</cbc:EstimatedOverallContractAmount></cac:RequestedTenderTotal><cac:MainCommodityClassification><cbc:ItemClassificationCode listName="cpv">45442100</cbc:ItemClassificationCode></cac:MainCommodityClassification><cac:RealizedLocation><cac:Address><cbc:CityName>Västerås</cbc:CityName><cbc:CountrySubentityCode listName="nuts">SE125</cbc:CountrySubentityCode><cac:Country><cbc:IdentificationCode listName="country">SWE</cbc:IdentificationCode></cac:Country></cac:Address></cac:RealizedLocation></cac:ProcurementProject><cac:ProcurementProjectLot><cbc:ID schemeName="Lot">LOT-0001</cbc:ID><cac:TenderingTerms><ext:UBLExtensions><ext:UBLExtension><ext:ExtensionContent><efext:EformsExtension><efac:SelectionCriteria><cbc:CriterionTypeCode listName="selection-criterion">ef-stand</cbc:CriterionTypeCode><cbc:CalculationExpressionCode listName="usage">used</cbc:CalculationExpressionCode></efac:SelectionCriteria><efac:SelectionCriteria><cbc:CriterionTypeCode listName="selection-criterion">sui-act</cbc:CriterionTypeCode><cbc:CalculationExpressionCode listName="usage">used</cbc:CalculationExpressionCode></efac:SelectionCriteria><efac:SelectionCriteria><cbc:CriterionTypeCode listName="selection-criterion">tp-abil</cbc:CriterionTypeCode><cbc:CalculationExpressionCode listName="usage">used</cbc:CalculationExpressionCode></efac:SelectionCriteria></efext:EformsExtension></ext:ExtensionContent></ext:UBLExtension></ext:UBLExtensions><cbc:FundingProgramCode listName="eu-funded">no-eu-funds</cbc:FundingProgramCode><cbc:RecurringProcurementIndicator>false</cbc:RecurringProcurementIndicator><cac:CallForTendersDocumentReference><cbc:ID>Länk till upphandlingsdokumenten</cbc:ID><cbc:DocumentType>non-restricted-document</cbc:DocumentType><cac:Attachment><cac:ExternalReference><cbc:URI>https://tendsign.com/doc.aspx?MeFormsNoticeId=42153</cbc:URI></cac:ExternalReference></cac:Attachment></cac:CallForTendersDocumentReference><cac:TendererQualificationRequest><cac:SpecificTendererRequirement><cbc:TendererRequirementTypeCode listName="reserved-procurement">none</cbc:TendererRequirementTypeCode></cac:SpecificTendererRequirement></cac:TendererQualificationRequest><cac:ContractExecutionRequirement><cbc:ExecutionRequirementCode listName="einvoicing">required</cbc:ExecutionRequirementCode></cac:ContractExecutionRequirement><cac:ContractExecutionRequirement><cbc:ExecutionRequirementCode listName="reserved-execution">not-known</cbc:ExecutionRequirementCode></cac:ContractExecutionRequirement><cac:ContractExecutionRequirement><cbc:ExecutionRequirementCode listName="ecatalog-submission">allowed</cbc:ExecutionRequirementCode></cac:ContractExecutionRequirement><cac:ContractExecutionRequirement><cbc:ExecutionRequirementCode listName="esignature-submission">false</cbc:ExecutionRequirementCode></cac:ContractExecutionRequirement><cac:TenderRecipientParty><cbc:EndpointID>https://tendsign.com/doc.aspx?MeFormsNoticeId=42153&amp;GoTo=Tender</cbc:EndpointID></cac:TenderRecipientParty><cac:TenderValidityPeriod><cbc:DurationMeasure unitCode="DAY">179</cbc:DurationMeasure></cac:TenderValidityPeriod><cac:AppealTerms><cac:AppealReceiverParty><cac:PartyIdentification><cbc:ID schemeName="organization">ORG-0002</cbc:ID></cac:PartyIdentification></cac:AppealReceiverParty></cac:AppealTerms><cac:Language><cbc:ID>SWE</cbc:ID></cac:Language><cac:PostAwardProcess><cbc:ElectronicOrderUsageIndicator>true</cbc:ElectronicOrderUsageIndicator><cbc:ElectronicPaymentUsageIndicator>true</cbc:ElectronicPaymentUsageIndicator></cac:PostAwardProcess></cac:TenderingTerms><cac:TenderingProcess><cbc:SubmissionMethodCode listName="esubmission">required</cbc:SubmissionMethodCode><cbc:GovernmentAgreementConstraintIndicator>false</cbc:GovernmentAgreementConstraintIndicator><cac:TenderSubmissionDeadlinePeriod><cbc:EndDate>2025-02-17+00:00</cbc:EndDate><cbc:EndTime>22:59:59+00:00</cbc:EndTime></cac:TenderSubmissionDeadlinePeriod><cac:AdditionalInformationRequestPeriod><cbc:EndDate>2025-02-06+00:00</cbc:EndDate><cbc:EndTime>23:00:00+00:00</cbc:EndTime></cac:AdditionalInformationRequestPeriod><cac:OpenTenderEvent><cbc:OccurrenceDate>2025-02-17+00:00</cbc:OccurrenceDate><cbc:OccurrenceTime>23:00:00+00:00</cbc:OccurrenceTime><cac:OccurenceLocation><cbc:Description languageID="SWE">Västerås</cbc:Description></cac:OccurenceLocation></cac:OpenTenderEvent><cac:AuctionTerms><cbc:AuctionConstraintIndicator>false</cbc:AuctionConstraintIndicator></cac:AuctionTerms><cac:ContractingSystem><cbc:ContractingSystemTypeCode listName="dps-usage">none</cbc:ContractingSystemTypeCode></cac:ContractingSystem><cac:ContractingSystem><cbc:ContractingSystemTypeCode listName="framework-agreement">fa-wo-rc</cbc:ContractingSystemTypeCode></cac:ContractingSystem></cac:TenderingProcess><cac:ProcurementProject><cbc:ID schemeName="InternalID">2024140</cbc:ID><cbc:Name languageID="SWE">Allmän del (1)</cbc:Name><cbc:Description languageID="SWE">Ramavtal för inre måleriarbeten (lägenhetsunderhåll) i beställarens fastighetsbestånd.</cbc:Description><cbc:ProcurementTypeCode listName="contract-nature">works</cbc:ProcurementTypeCode><cac:ProcurementAdditionalType><cbc:ProcurementTypeCode listName="strategic-procurement">env-imp</cbc:ProcurementTypeCode></cac:ProcurementAdditionalType><cac:RequestedTenderTotal><cbc:EstimatedOverallContractAmount currencyID="SEK">60000000</cbc:EstimatedOverallContractAmount></cac:RequestedTenderTotal><cac:MainCommodityClassification><cbc:ItemClassificationCode listName="cpv">45442100</cbc:ItemClassificationCode></cac:MainCommodityClassification><cac:RealizedLocation><cac:Address><cbc:CountrySubentityCode listName="nuts">SE125</cbc:CountrySubentityCode><cac:Country><cbc:IdentificationCode listName="country">SWE</cbc:IdentificationCode></cac:Country></cac:Address></cac:RealizedLocation><cac:PlannedPeriod><cbc:StartDate>2025-05-01Z</cbc:StartDate><cbc:EndDate>2027-04-30Z</cbc:EndDate></cac:PlannedPeriod><cac:ContractExtension><cbc:MaximumNumberNumeric>2</cbc:MaximumNumberNumeric><cac:Renewal><cac:Period><cbc:Description languageID="SWE">Förlängning är 12 månader</cbc:Description></cac:Period></cac:Renewal></cac:ContractExtension></cac:ProcurementProject></cac:ProcurementProjectLot><cac:ProcurementProjectLot><cbc:ID schemeName="Lot">LOT-0002</cbc:ID><cac:TenderingTerms><ext:UBLExtensions><ext:UBLExtension><ext:ExtensionContent><efext:EformsExtension><efac:SelectionCriteria><cbc:CriterionTypeCode listName="selection-criterion">ef-stand</cbc:CriterionTypeCode><cbc:CalculationExpressionCode listName="usage">used</cbc:CalculationExpressionCode></efac:SelectionCriteria><efac:SelectionCriteria><cbc:CriterionTypeCode listName="selection-criterion">sui-act</cbc:CriterionTypeCode><cbc:CalculationExpressionCode listName="usage">used</cbc:CalculationExpressionCode></efac:SelectionCriteria><efac:SelectionCriteria><cbc:CriterionTypeCode listName="selection-criterion">tp-abil</cbc:CriterionTypeCode><cbc:CalculationExpressionCode listName="usage">used</cbc:CalculationExpressionCode></efac:SelectionCriteria></efext:EformsExtension></ext:ExtensionContent></ext:UBLExtension></ext:UBLExtensions><cbc:FundingProgramCode listName="eu-funded">no-eu-funds</cbc:FundingProgramCode><cbc:RecurringProcurementIndicator>false</cbc:RecurringProcurementIndicator><cac:CallForTendersDocumentReference><cbc:ID>Länk till upphandlingsdokumenten</cbc:ID><cbc:DocumentType>non-restricted-document</cbc:DocumentType><cac:Attachment><cac:ExternalReference><cbc:URI>https://tendsign.com/doc.aspx?MeFormsNoticeId=42153</cbc:URI></cac:ExternalReference></cac:Attachment></cac:CallForTendersDocumentReference><cac:TendererQualificationRequest><cac:SpecificTendererRequirement><cbc:TendererRequirementTypeCode listName="reserved-procurement">none</cbc:TendererRequirementTypeCode></cac:SpecificTendererRequirement></cac:TendererQualificationRequest><cac:ContractExecutionRequirement><cbc:ExecutionRequirementCode listName="einvoicing">required</cbc:ExecutionRequirementCode></cac:ContractExecutionRequirement><cac:ContractExecutionRequirement><cbc:ExecutionRequirementCode listName="reserved-execution">not-known</cbc:ExecutionRequirementCode></cac:ContractExecutionRequirement><cac:ContractExecutionRequirement><cbc:ExecutionRequirementCode listName="ecatalog-submission">allowed</cbc:ExecutionRequirementCode></cac:ContractExecutionRequirement><cac:ContractExecutionRequirement><cbc:ExecutionRequirementCode listName="esignature-submission">false</cbc:ExecutionRequirementCode></cac:ContractExecutionRequirement><cac:TenderRecipientParty><cbc:EndpointID>https://tendsign.com/doc.aspx?MeFormsNoticeId=42153&amp;GoTo=Tender</cbc:EndpointID></cac:TenderRecipientParty><cac:TenderValidityPeriod><cbc:DurationMeasure unitCode="DAY">179</cbc:DurationMeasure></cac:TenderValidityPeriod><cac:AppealTerms><cac:AppealReceiverParty><cac:PartyIdentification><cbc:ID schemeName="organization">ORG-0002</cbc:ID></cac:PartyIdentification></cac:AppealReceiverParty></cac:AppealTerms><cac:Language><cbc:ID>SWE</cbc:ID></cac:Language><cac:PostAwardProcess><cbc:ElectronicOrderUsageIndicator>true</cbc:ElectronicOrderUsageIndicator><cbc:ElectronicPaymentUsageIndicator>true</cbc:ElectronicPaymentUsageIndicator></cac:PostAwardProcess></cac:TenderingTerms><cac:TenderingProcess><cbc:SubmissionMethodCode listName="esubmission">required</cbc:SubmissionMethodCode><cbc:GovernmentAgreementConstraintIndicator>false</cbc:GovernmentAgreementConstraintIndicator><cac:TenderSubmissionDeadlinePeriod><cbc:EndDate>2025-02-17+00:00</cbc:EndDate><cbc:EndTime>22:59:59+00:00</cbc:EndTime></cac:TenderSubmissionDeadlinePeriod><cac:AdditionalInformationRequestPeriod><cbc:EndDate>2025-02-06+00:00</cbc:EndDate><cbc:EndTime>23:00:00+00:00</cbc:EndTime></cac:AdditionalInformationRequestPeriod><cac:OpenTenderEvent><cbc:OccurrenceDate>2025-02-17+00:00</cbc:OccurrenceDate><cbc:OccurrenceTime>23:00:00+00:00</cbc:OccurrenceTime><cac:OccurenceLocation><cbc:Description languageID="SWE">Västerås</cbc:Description></cac:OccurenceLocation></cac:OpenTenderEvent><cac:AuctionTerms><cbc:AuctionConstraintIndicator>false</cbc:AuctionConstraintIndicator></cac:AuctionTerms><cac:ContractingSystem><cbc:ContractingSystemTypeCode listName="dps-usage">none</cbc:ContractingSystemTypeCode></cac:ContractingSystem><cac:ContractingSystem><cbc:ContractingSystemTypeCode listName="framework-agreement">fa-wo-rc</cbc:ContractingSystemTypeCode></cac:ContractingSystem></cac:TenderingProcess><cac:ProcurementProject><cbc:ID schemeName="InternalID">2024140</cbc:ID><cbc:Name languageID="SWE">Egenförsäkran</cbc:Name><cbc:Description languageID="SWE">Anbudsgivare lämnar anbud genom en egenförsäkran och kommer därmed kontrolleras med efterfrågad bevisning vid behov under upphandlingsprocessen, men som senast
innan tilldelning (i det fall anbudsgivare är i läge för tilldelning).

Anbudsgivare som lämnar anbud genom egenförsäkran behöver inte fylla i del "Sanningsförsäkran och kvalificeringskrav".</cbc:Description><cbc:ProcurementTypeCode listName="contract-nature">works</cbc:ProcurementTypeCode><cac:ProcurementAdditionalType><cbc:ProcurementTypeCode listName="strategic-procurement">env-imp</cbc:ProcurementTypeCode></cac:ProcurementAdditionalType><cac:RequestedTenderTotal><cbc:EstimatedOverallContractAmount currencyID="SEK">60000000</cbc:EstimatedOverallContractAmount></cac:RequestedTenderTotal><cac:MainCommodityClassification><cbc:ItemClassificationCode listName="cpv">45442100</cbc:ItemClassificationCode></cac:MainCommodityClassification><cac:RealizedLocation><cac:Address><cbc:CountrySubentityCode listName="nuts">SE125</cbc:CountrySubentityCode><cac:Country><cbc:IdentificationCode listName="country">SWE</cbc:IdentificationCode></cac:Country></cac:Address></cac:RealizedLocation><cac:PlannedPeriod><cbc:StartDate>2025-05-01Z</cbc:StartDate><cbc:EndDate>2027-04-30Z</cbc:EndDate></cac:PlannedPeriod><cac:ContractExtension><cbc:MaximumNumberNumeric>2</cbc:MaximumNumberNumeric><cac:Renewal><cac:Period><cbc:Description languageID="SWE">Förlängning är 12 månader</cbc:Description></cac:Period></cac:Renewal></cac:ContractExtension></cac:ProcurementProject></cac:ProcurementProjectLot><cac:ProcurementProjectLot><cbc:ID schemeName="Lot">LOT-0003</cbc:ID><cac:TenderingTerms><ext:UBLExtensions><ext:UBLExtension><ext:ExtensionContent><efext:EformsExtension><efac:SelectionCriteria><cbc:CriterionTypeCode listName="selection-criterion">ef-stand</cbc:CriterionTypeCode><cbc:CalculationExpressionCode listName="usage">used</cbc:CalculationExpressionCode></efac:SelectionCriteria><efac:SelectionCriteria><cbc:CriterionTypeCode listName="selection-criterion">sui-act</cbc:CriterionTypeCode><cbc:CalculationExpressionCode listName="usage">used</cbc:CalculationExpressionCode></efac:SelectionCriteria><efac:SelectionCriteria><cbc:CriterionTypeCode listName="selection-criterion">tp-abil</cbc:CriterionTypeCode><cbc:CalculationExpressionCode listName="usage">used</cbc:CalculationExpressionCode></efac:SelectionCriteria></efext:EformsExtension></ext:ExtensionContent></ext:UBLExtension></ext:UBLExtensions><cbc:FundingProgramCode listName="eu-funded">no-eu-funds</cbc:FundingProgramCode><cbc:RecurringProcurementIndicator>false</cbc:RecurringProcurementIndicator><cac:CallForTendersDocumentReference><cbc:ID>Länk till upphandlingsdokumenten</cbc:ID><cbc:DocumentType>non-restricted-document</cbc:DocumentType><cac:Attachment><cac:ExternalReference><cbc:URI>https://tendsign.com/doc.aspx?MeFormsNoticeId=42153</cbc:URI></cac:ExternalReference></cac:Attachment></cac:CallForTendersDocumentReference><cac:TendererQualificationRequest><cac:SpecificTendererRequirement><cbc:TendererRequirementTypeCode listName="reserved-procurement">none</cbc:TendererRequirementTypeCode></cac:SpecificTendererRequirement></cac:TendererQualificationRequest><cac:ContractExecutionRequirement><cbc:ExecutionRequirementCode listName="einvoicing">required</cbc:ExecutionRequirementCode></cac:ContractExecutionRequirement><cac:ContractExecutionRequirement><cbc:ExecutionRequirementCode listName="reserved-execution">not-known</cbc:ExecutionRequirementCode></cac:ContractExecutionRequirement><cac:ContractExecutionRequirement><cbc:ExecutionRequirementCode listName="ecatalog-submission">allowed</cbc:ExecutionRequirementCode></cac:ContractExecutionRequirement><cac:ContractExecutionRequirement><cbc:ExecutionRequirementCode listName="esignature-submission">false</cbc:ExecutionRequirementCode></cac:ContractExecutionRequirement><cac:TenderRecipientParty><cbc:EndpointID>https://tendsign.com/doc.aspx?MeFormsNoticeId=42153&amp;GoTo=Tender</cbc:EndpointID></cac:TenderRecipientParty><cac:TenderValidityPeriod><cbc:DurationMeasure unitCode="DAY">179</cbc:DurationMeasure></cac:TenderValidityPeriod><cac:AppealTerms><cac:AppealReceiverParty><cac:PartyIdentification><cbc:ID schemeName="organization">ORG-0002</cbc:ID></cac:PartyIdentification></cac:AppealReceiverParty></cac:AppealTerms><cac:Language><cbc:ID>SWE</cbc:ID></cac:Language><cac:PostAwardProcess><cbc:ElectronicOrderUsageIndicator>true</cbc:ElectronicOrderUsageIndicator><cbc:ElectronicPaymentUsageIndicator>true</cbc:ElectronicPaymentUsageIndicator></cac:PostAwardProcess></cac:TenderingTerms><cac:TenderingProcess><cbc:SubmissionMethodCode listName="esubmission">required</cbc:SubmissionMethodCode><cbc:GovernmentAgreementConstraintIndicator>false</cbc:GovernmentAgreementConstraintIndicator><cac:TenderSubmissionDeadlinePeriod><cbc:EndDate>2025-02-17+00:00</cbc:EndDate><cbc:EndTime>22:59:59+00:00</cbc:EndTime></cac:TenderSubmissionDeadlinePeriod><cac:AdditionalInformationRequestPeriod><cbc:EndDate>2025-02-06+00:00</cbc:EndDate><cbc:EndTime>23:00:00+00:00</cbc:EndTime></cac:AdditionalInformationRequestPeriod><cac:OpenTenderEvent><cbc:OccurrenceDate>2025-02-17+00:00</cbc:OccurrenceDate><cbc:OccurrenceTime>23:00:00+00:00</cbc:OccurrenceTime><cac:OccurenceLocation><cbc:Description languageID="SWE">Västerås</cbc:Description></cac:OccurenceLocation></cac:OpenTenderEvent><cac:AuctionTerms><cbc:AuctionConstraintIndicator>false</cbc:AuctionConstraintIndicator></cac:AuctionTerms><cac:ContractingSystem><cbc:ContractingSystemTypeCode listName="dps-usage">none</cbc:ContractingSystemTypeCode></cac:ContractingSystem><cac:ContractingSystem><cbc:ContractingSystemTypeCode listName="framework-agreement">fa-wo-rc</cbc:ContractingSystemTypeCode></cac:ContractingSystem></cac:TenderingProcess><cac:ProcurementProject><cbc:ID schemeName="InternalID">2024140</cbc:ID><cbc:Name languageID="SWE">Sanningsförsäkran och kvalificeringskrav</cbc:Name><cbc:Description languageID="SWE">Anbudsgivare lämnar anbud genom att intyga genom en sanningsförsäkran att denne inte berörs av någon av de uteslutningsgrunder som framgår av 13 kap 1-3 §§ LOU och besvara Beställarens uppställda kvalificeringskrav. Anbudsgivare som lämnar anbud genom sanningsförsäkran behöver inte fylla i del "Egenförsäkran".</cbc:Description><cbc:ProcurementTypeCode listName="contract-nature">works</cbc:ProcurementTypeCode><cac:ProcurementAdditionalType><cbc:ProcurementTypeCode listName="strategic-procurement">env-imp</cbc:ProcurementTypeCode></cac:ProcurementAdditionalType><cac:RequestedTenderTotal><cbc:EstimatedOverallContractAmount currencyID="SEK">60000000</cbc:EstimatedOverallContractAmount></cac:RequestedTenderTotal><cac:MainCommodityClassification><cbc:ItemClassificationCode listName="cpv">45442100</cbc:ItemClassificationCode></cac:MainCommodityClassification><cac:RealizedLocation><cac:Address><cbc:CountrySubentityCode listName="nuts">SE125</cbc:CountrySubentityCode><cac:Country><cbc:IdentificationCode listName="country">SWE</cbc:IdentificationCode></cac:Country></cac:Address></cac:RealizedLocation><cac:PlannedPeriod><cbc:StartDate>2025-05-01Z</cbc:StartDate><cbc:EndDate>2027-04-30Z</cbc:EndDate></cac:PlannedPeriod><cac:ContractExtension><cbc:MaximumNumberNumeric>2</cbc:MaximumNumberNumeric><cac:Renewal><cac:Period><cbc:Description languageID="SWE">Förlängning är 12 månader</cbc:Description></cac:Period></cac:Renewal></cac:ContractExtension></cac:ProcurementProject></cac:ProcurementProjectLot></ContractNotice>